{"id":"D370F7E4-AA2A-46B4-9B90-5D08F967B52F","validationEntity":{"analysedDataType":"auto","dataResult":{}},"modelEntity":{"createdDate":"2020-11-17T10:19:30Z","id":"89539338-54F3-4DEB-B9C3-188ABF81EEC7","experimentID":"F8845690-0BFE-4FF4-A20E-A32E977E151A","title":"","modifiedDate":"2020-11-17T10:19:30Z","preferredFilename":"","version":"1.0","modelURL":"Models\/FontWeightClassifier%201%20copy.mlmodel"},"version":"1.0","settingEntity":{"taskType":"imageClassifier","augmentations":[],"styleTransferAlgorithmType":"image","iterationCount":50,"transferLearningEmbeddingType":"dynamic","harVideoAugmentations":0,"algorithmType":"maxEnt","seedType":"default","featureNames":[]},"state":"trained","trainingEntity":{"finishTime":"2020-11-17T10:20:18Z","recipeTrainingResults":{"imageClassifier":{"confusionMatrix":[{"expected":"regular","actual":"regular","count":74},{"expected":"semibold","actual":"semibold","count":57}],"statsByLabel":{"regular":{"count":74,"precisionRecall":{"success":{"recall":1,"precision":1}}},"semibold":{"count":57,"precisionRecall":{"success":{"recall":1,"precision":1}}}},"accuracy":1}},"dataResult":{"itemsCount":147,"dataURL":"file:\/\/\/Users\/ipdesign\/Box\/MyShare\/DataSet\/Weight\/","classesCount":2,"dataSourceID":"E0CC6236-1395-47BB-834D-7A448479B7F7","analysis":{"summary":{"sampleCount":147,"classCount":2,"canUseValidation":1},"issues":[{"description":"2 classes found, including regular, semibold","severity":"debug"},{"description":"147 images found, automatically creating validation set","severity":"good"},{"description":"Smallest class is \"semibold\" with 66 images","severity":"debug"},{"description":"Largest class is \"regular\" with 81 images","severity":"debug"}],"classifierAnalysis":{"columns":[],"vizualizerSpec":"","labelStats":{"regular":81,"semibold":66}}}},"dataURL":"file:\/\/\/Users\/ipdesign\/Box\/MyShare\/DataSet\/Weight\/","featureExtractionCheckpointMayBeAvailable":false,"recipeValidationResults":{"imageClassifier":{"confusionMatrix":[{"expected":"regular","actual":"regular","count":5},{"expected":"semibold","actual":"regular","count":2},{"expected":"regular","actual":"semibold","count":3},{"expected":"semibold","actual":"semibold","count":6}],"statsByLabel":{"regular":{"count":7,"precisionRecall":{"success":{"recall":0.7142857142857143,"precision":0.625}}},"semibold":{"count":9,"precisionRecall":{"success":{"recall":0.66666666666666663,"precision":0.75}}}},"accuracy":0.6875}},"progress":[{"icTrainingColumnHeader":{"hasValidation":true,"elapsedTime":0.132327,"trainingAccuracy":0.56488499999999997,"iterationCount":1,"validationAccuracy":0.4375},"isLast":false,"currentRowIndex":0,"count":1,"tableDone":false,"tableIndex":2,"percentComplete":0},{"icTrainingColumnHeader":{"hasValidation":true,"elapsedTime":0.345833,"trainingAccuracy":0.77862600000000004,"iterationCount":2,"validationAccuracy":0.375},"isLast":false,"currentRowIndex":0,"count":2,"tableDone":false,"tableIndex":2,"percentComplete":0},{"icTrainingColumnHeader":{"hasValidation":true,"elapsedTime":0.40279700000000002,"trainingAccuracy":0.89312999999999998,"iterationCount":3,"validationAccuracy":0.75},"isLast":false,"currentRowIndex":0,"count":3,"tableDone":false,"tableIndex":2,"percentComplete":0},{"icTrainingColumnHeader":{"hasValidation":true,"elapsedTime":0.503992,"trainingAccuracy":0.87022900000000003,"iterationCount":4,"validationAccuracy":0.6875},"isLast":false,"currentRowIndex":0,"count":4,"tableDone":false,"tableIndex":2,"percentComplete":0},{"icTrainingColumnHeader":{"hasValidation":true,"elapsedTime":0.60524500000000003,"trainingAccuracy":0.99236599999999997,"iterationCount":5,"validationAccuracy":0.8125},"isLast":false,"currentRowIndex":0,"count":5,"tableDone":false,"tableIndex":2,"percentComplete":0},{"icTrainingColumnHeader":{"hasValidation":true,"elapsedTime":0.92054599999999998,"trainingAccuracy":1,"iterationCount":10,"validationAccuracy":0.6875},"isLast":false,"currentRowIndex":0,"count":10,"tableDone":false,"tableIndex":2,"percentComplete":0},{"icTrainingColumnHeader":{"hasValidation":true,"elapsedTime":1.4614990000000001,"trainingAccuracy":1,"iterationCount":17,"validationAccuracy":0.6875},"isLast":false,"currentRowIndex":0,"count":17,"tableDone":true,"tableIndex":2,"percentComplete":0},{"currentRowIndex":0,"tableIndex":0,"count":50,"isLast":false,"percentComplete":0,"tableDone":false},{"currentRowIndex":0,"tableIndex":0,"count":100,"isLast":false,"percentComplete":0,"tableDone":false}],"trainingAccuracy":1,"checkpointMetrics":{},"analysedDataType":"datasource","dataSourceID":"E0CC6236-1395-47BB-834D-7A448479B7F7","snapshottableCheckpoints":{},"validationAccuracy":0.6875,"startTime":"2020-11-17T10:20:09Z"},"createdDate":"2020-11-17T10:19:30Z","snapshotRole":{"withoutSnapshots":0},"evaluationEntities":[],"activityEntities":["experimentCreated",[{"id":"1EF807B3-E07E-43EF-B9AF-FCB37AFEB009","title":"Model Source Created","createdDate":"2020-11-17T10:19:30Z","event":"experimentCreated","subtitle":"FontWeightClassifier 1 copy"}],"trainingDataAdded",[{"id":"67F1F806-19EA-473B-88F1-C819F3DE5614","title":"Training Data Added","createdDate":"2020-11-17T10:19:35Z","event":"trainingDataAdded","subtitle":"Weight"}],"trainingFinished",[{"id":"403CEB18-0655-42AD-A4BA-2AEFF9603864","title":"Training Completed","createdDate":"2020-11-17T10:20:18Z","event":"trainingFinished","subtitle":"Model converged at 17 iterations"}],"trainingStarted",[{"id":"702253BE-1001-46D2-847C-9C3A85A28235","title":"Training Started","createdDate":"2020-11-17T10:20:09Z","event":"trainingStarted","subtitle":"50 iterations"}]],"title":"FontWeightClassifier 1 copy","evaluationEntity":{"id":"26adee90-1c05-44d4-b2a8-69723f16cb26","analysedDataType":"none","dataResult":{}},"evaluationState":"uninitialized","contentDataResult":{},"modifiedDate":"2020-11-17T10:20:18Z","preferredFilename":"FontWeightClassifier 1 copy"}